meter_proving/__init__.py
meter_proving/meter_proving.py
meter_proving-1.0.0.dist-info/METADATA
meter_proving-1.0.0.dist-info/WHEEL
meter_proving-1.0.0.dist-info/RECORD
