Metadata-Version: 2.1
Name: meter_proving
Version: 1.0.0
Summary: library to calculate random uncertanity of a measurment sequence
Author: StigHaraldGustavsen
Author-email: stighg@gmail.com
Requires-Python: >=3.10,<4.0
Classifier: Programming Language :: Python :: 3
Classifier: Programming Language :: Python :: 3.10
Classifier: Programming Language :: Python :: 3.11
Classifier: Programming Language :: Python :: 3.12
Requires-Dist: numba (>=0.56.4,<0.57.0)
